setup.cfg
setup.py
raspy.egg-info/PKG-INFO
raspy.egg-info/SOURCES.txt
raspy.egg-info/dependency_links.txt
raspy.egg-info/top_level.txt
raspy/output/__init__.py
raspy/sensors/__init__.py