Metadata-Version: 1.0
Name: raspy
Version: 0.1
Summary: Raspberry Pi Functions from Kyle
Home-page: http://github.com/kylecorry31/RPy
Author: Kyle Corry
Author-email: kylecorry31@gmail.com
License: UNKNOWN
Platform: UNKNOWN
